appsignal_logging/__init__.py
appsignal_logging/handlers.py
appsignal_logging-0.1.1.dist-info/licenses/LICENSE
appsignal_logging-0.1.1.dist-info/METADATA
appsignal_logging-0.1.1.dist-info/WHEEL
appsignal_logging-0.1.1.dist-info/top_level.txt
appsignal_logging-0.1.1.dist-info/RECORD
