Metadata-Version: 2.4
Name: appsignal-logging
Version: 0.1.1
Summary: Python logging handlers for AppSignal with HTTP and NDJSON support
Author-email: Dmitriy Trochshenko <dmitriy.trochshenko@gmail.com>
License: MIT
Project-URL: Homepage, https://github.com/magicjohnon/appsignal-logging-python
Project-URL: Documentation, https://github.com/magicjohnon/appsignal-logging-python#readme
Project-URL: Repository, https://github.com/magicjohnon/appsignal-logging-python
Project-URL: Issues, https://github.com/magicjohnon/appsignal-logging-python/issues
Keywords: appsignal,logging,monitoring,ndjson,http
Classifier: Development Status :: 4 - Beta
Classifier: Intended Audience :: Developers
Classifier: License :: OSI Approved :: MIT License
Classifier: Programming Language :: Python :: 3
Classifier: Programming Language :: Python :: 3.10
Classifier: Programming Language :: Python :: 3.11
Classifier: Programming Language :: Python :: 3.12
Classifier: Topic :: System :: Logging
Classifier: Topic :: Software Development :: Libraries :: Python Modules
Requires-Python: >=3.8
License-File: LICENSE
Requires-Dist: httpx>=0.24.0
Provides-Extra: dev
Requires-Dist: pytest>=7.0.0; extra == "dev"
Requires-Dist: pytest-cov>=4.0.0; extra == "dev"
Requires-Dist: black>=23.0.0; extra == "dev"
Requires-Dist: ruff>=0.1.0; extra == "dev"
Requires-Dist: mypy>=1.0.0; extra == "dev"
Requires-Dist: build>=1.3.0; extra == "dev"
Dynamic: license-file
